markdown_mermaidjs/__init__.py
markdown_mermaidjs/markdown_mermaidjs.py
markdown_mermaidjs-2.0.0.dist-info/METADATA
markdown_mermaidjs-2.0.0.dist-info/WHEEL
markdown_mermaidjs-2.0.0.dist-info/licenses/LICENSE
markdown_mermaidjs-2.0.0.dist-info/RECORD
