Metadata-Version: 2.4
Name: markdown-mermaidjs
Version: 2.0.0
Summary: Python-Markdown extension to add Mermaid graph
Project-URL: Source, https://github.com/Lee-W/markdown-mermaidjs
Author-email: Wei Lee <weilee.rx@gmail.com>, Owyn Richen <owynrichen@gmail.com>
License-Expression: GPL-3.0-only
License-File: LICENSE
Classifier: Development Status :: 4 - Beta
Classifier: Intended Audience :: Developers
Classifier: License :: OSI Approved :: GNU General Public License v3 (GPLv3)
Classifier: Operating System :: OS Independent
Classifier: Programming Language :: Python
Classifier: Topic :: Text Processing :: Filters
Classifier: Topic :: Text Processing :: Markup :: HTML
Requires-Python: >=3.9
Requires-Dist: markdown>=3.7
